README.rst
setup.cfg
setup.py
apitracker_agent/__init__.py
apitracker_agent/base.py
apitracker_agent/events.py
apitracker_agent/processors.py
apitracker_agent/version.py
apitracker_agent.egg-info/PKG-INFO
apitracker_agent.egg-info/SOURCES.txt
apitracker_agent.egg-info/dependency_links.txt
apitracker_agent.egg-info/entry_points.txt
apitracker_agent.egg-info/not-zip-safe
apitracker_agent.egg-info/requires.txt
apitracker_agent.egg-info/top_level.txt
apitracker_agent/conf/__init__.py
apitracker_agent/conf/constants.py
apitracker_agent/context/__init__.py
apitracker_agent/context/base.py
apitracker_agent/context/contextvars.py
apitracker_agent/context/threadlocal.py
apitracker_agent/contrib/__init__.py
apitracker_agent/contrib/async_worker.py
apitracker_agent/instrumentation/__init__.py
apitracker_agent/instrumentation/control.py
apitracker_agent/instrumentation/packages/__init__.py
apitracker_agent/instrumentation/packages/base.py
apitracker_agent/instrumentation/packages/httpclient.py
apitracker_agent/transport/__init__.py
apitracker_agent/transport/base.py
apitracker_agent/transport/exceptions.py
apitracker_agent/transport/http.py
apitracker_agent/transport/http_base.py
apitracker_agent/utils/__init__.py
apitracker_agent/utils/compat.py
apitracker_agent/utils/encoding.py
apitracker_agent/utils/json_encoder.py
apitracker_agent/utils/logging.py
apitracker_agent/utils/module_import.py
apitracker_agent/utils/threading.py